w3off/__init__.py
w3off/__main__.py
w3off/chains.yaml
w3off/config.py
w3off/w3main.py
w3off/w3provider.py
w3off/cli/__init__.py
w3off/cli/helpers.py
w3off/cli/prompts.py
w3off/helpers/__init__.py
w3off/helpers/abiHelpers.py
w3off/helpers/addressHelpers.py
w3off/helpers/txHelpers.py
w3off/observer/__init__.py
w3off/observer/__main__.py
w3off/observer/cache.py
w3off/observer/fetchABI.py
w3off/observer/w3observer.py
w3off/observer/shortcuts/__init__.py
w3off/observer/shortcuts/customTx.py
w3off/observer/shortcuts/erc20Tx.py
w3off/sender/__init__.py
w3off/sender/__main__.py
w3off/sender/w3sender.py
w3off/signer/__init__.py
w3off/signer/__main__.py
w3off/signer/checkOffline.py
w3off/signer/vault.py
w3off/signer/w3signer.py
w3off/test/__init__.py
w3off/test/ethTesterContracts.py
w3off/test/ethTesterEnv.py
w3off/test/test_helpers.py
w3off/test/test_observer.py
w3off/test/test_sender.py
w3off/test/test_signer.py
w3off/test/test_w3off.py
w3off/test/data/aave_v3.abi
w3off/test/data/keystore-default.json
w3off/test/data/keystore-test.json
w3off/test/data/keystore-test2.json
w3off/test/data/lido.abi
w3off/test/data/sky.abi
w3off/test/data/txTestAaveSupply.py
w3off/test/data/txTestEthTransfer.py
w3off/test/data/txTestUSDTTransfer.py
w3off/test/data/usdc.abi
w3off/test/data/usdt.abi
w3off/test/data/usdt1.abi
w3off-0.2.0.dist-info/LICENSE
w3off-0.2.0.dist-info/METADATA
w3off-0.2.0.dist-info/WHEEL
w3off-0.2.0.dist-info/entry_points.txt
w3off-0.2.0.dist-info/top_level.txt
w3off-0.2.0.dist-info/RECORD
