Metadata-Version: 2.2
Name: w3off
Version: 0.2.0
Summary: Collection of CLI utilities for secure offline blockchain transaction creation and signing
License:                                  Apache License
Project-URL: Homepage, https://github.com/roman-spiridonov/w3off
Project-URL: Repository, https://github.com/roman-spiridonov/w3off
Project-URL: Issues, https://github.com/roman-spiridonov/w3off/issues
Keywords: web3,offline-wallet,ethereum,evm,crypto,blockchain,smart-contracts
Classifier: Development Status :: 4 - Beta
Classifier: Programming Language :: Python :: 3
Classifier: Programming Language :: Python :: 3.12
Requires-Python: >=3.12
License-File: LICENSE
Requires-Dist: web3
Requires-Dist: eth_tester
Requires-Dist: py-evm
Requires-Dist: pyyaml
